kivy_garden/xcamera/__init__.py
kivy_garden/xcamera/android_api.py
kivy_garden/xcamera/main.py
kivy_garden/xcamera/platform_api.py
kivy_garden/xcamera/version.py
kivy_garden/xcamera/xcamera.kv
kivy_garden/xcamera/xcamera.py
kivy_garden/xcamera/data/icons.ttf
kivy_garden/xcamera/data/shutter.wav
xcamera-2020.613.dist-info/LICENSE
xcamera-2020.613.dist-info/METADATA
xcamera-2020.613.dist-info/WHEEL
xcamera-2020.613.dist-info/entry_points.txt
xcamera-2020.613.dist-info/top_level.txt
xcamera-2020.613.dist-info/RECORD
